[{"index": 1, "isLeaf": true, "children": [null, null, null, null], "items": {"key": 664, "value": 0.02}, "numberOfkeys": 1}, {"index": 2, "isLeaf": false, "children": [1, 3, 4, 5], "items": {"key": 673, "value": 0.05}, "numberOfkeys": 1}, {"index": 3, "isLeaf": true, "children": [null, null, null, null], "items": {"key": 671, "value": 0.04}, "numberOfkeys": 1}, {"index": 4, "isLeaf": true, "children": [null, null, null, null], "items": {"key": 681, "value": 0.07}, "numberOfkeys": 1}, {"index": 5, "isLeaf": true, "children": [null, null, null, null], "items": {"key": 689, "value": 0.09}, "numberOfkeys": 1}, {"index": 6, "isLeaf": false, "children": [2, 7, 10, 13], "items": {"key": 699, "value": 0.13}, "numberOfkeys": 1}, {"index": 7, "isLeaf": false, "children": [4, 5, 8, 9], "items": {"key": 692, "value": 0.1}, "numberOfkeys": 1}, {"index": 8, "isLeaf": true, "children": [null, null, null, null], "items": {"key": 695, "value": 0.12}, "numberOfkeys": 1}, {"index": 9, "isLeaf": true, "children": [null, null, null, null], "items": {"key": 700, "value": 0.14}, "numberOfkeys": 1}, {"index": 10, "isLeaf": false, "children": [8, 9, 11, 12], "items": {"key": 701, "value": 0.15}, "numberOfkeys": 1}, {"index": 11, "isLeaf": true, "children": [null, null, null, null], "items": {"key": 705, "value": 0.16}, "numberOfkeys": 1}, {"index": 12, "isLeaf": true, "children": [null, null, null, null], "items": {"key": 710, "value": 0.18}, "numberOfkeys": 1}, {"index": 13, "isLeaf": false, "children": [11, 12, 16, 17], "items": {"key": 716, "value": 0.19}, "numberOfkeys": 1}, {"index": 14, "isLeaf": false, "children": [6, 15, 22, 29], "items": {"key": 723, "value": 0.27}, "numberOfkeys": 1}, {"index": 15, "isLeaf": false, "children": [10, 13, 18, 21], "items": {"key": 719, "value": 0.21}, "numberOfkeys": 1}, {"index": 16, "isLeaf": true, "children": [null, null, null, null], "items": {"key": 718, "value": 0.2}, "numberOfkeys": 1}, {"index": 17, "isLeaf": true, "children": [null, null, null, null], "items": {"key": 720, "value": 0.23}, "numberOfkeys": 1}, {"index": 18, "isLeaf": false, "children": [16, 17, 19, 20], "items": {"key": 721, "value": 0.24}, "numberOfkeys": 1}, {"index": 19, "isLeaf": true, "children": [null, null, null, null], "items": {"key": 722, "value": 0.26}, "numberOfkeys": 1}, {"index": 20, "isLeaf": true, "children": [null, null, null, null], "items": {"key": 724, "value": 0.28}, "numberOfkeys": 1}, {"index": 21, "isLeaf": false, "children": [19, 20, 23, 24], "items": {"key": 725, "value": 0.3}, "numberOfkeys": 1}, {"index": 22, "isLeaf": false, "children": [18, 21, 25, 28], "items": {"key": 728, "value": 0.32}, "numberOfkeys": 1}, {"index": 23, "isLeaf": true, "children": [null, null, null, null], "items": {"key": 727, "value": 0.31}, "numberOfkeys": 1}, {"index": 24, "isLeaf": true, "children": [null, null, null, null], "items": {"key": 730, "value": 0.33}, "numberOfkeys": 1}, {"index": 25, "isLeaf": false, "children": [23, 24, 26, 27], "items": {"key": 733, "value": 0.34}, "numberOfkeys": 1}, {"index": 26, "isLeaf": true, "children": [null, null, null, null], "items": {"key": 734, "value": 0.35}, "numberOfkeys": 1}, {"index": 27, "isLeaf": true, "children": [null, null, null, null], "items": {"key": 737, "value": 0.39}, "numberOfkeys": 1}, {"index": 28, "isLeaf": false, "children": [26, 27, 30, 33], "items": {"key": 738, "value": 0.42}, "numberOfkeys": 1}, {"index": 29, "isLeaf": false, "children": [25, 28, 34, 37], "items": {"key": 740, "value": 0.45}, "numberOfkeys": 1}, {"index": 30, "isLeaf": true, "children": [null, null, null, null], "items": {"key": 739, "value": 0.43}, "numberOfkeys": 1}, {"index": 31, "isLeaf": false, "children": [14, 32, 47, 62], "items": {"key": 755, "value": 0.68}, "numberOfkeys": 1}, {"index": 32, "isLeaf": false, "children": [22, 29, 38, 45], "items": {"key": 746, "value": 0.49}, "numberOfkeys": 1}, {"index": 33, "isLeaf": true, "children": [null, null, null, null], "items": {"key": 741, "value": 0.46}, "numberOfkeys": 1}, {"index": 34, "isLeaf": false, "children": [30, 33, 35, 36], "items": {"key": 742, "value": 0.47}, "numberOfkeys": 1}, {"index": 35, "isLeaf": true, "children": [null, null, null, null], "items": {"key": 743, "value": 0.48}, "numberOfkeys": 1}, {"index": 36, "isLeaf": true, "children": [null, null, null, null], "items": {"key": 747, "value": 0.5}, "numberOfkeys": 1}, {"index": 37, "isLeaf": false, "children": [35, 36, 39, 40], "items": {"key": 749, "value": 0.54}, "numberOfkeys": 1}, {"index": 38, "isLeaf": false, "children": [34, 37, 41, 44], "items": {"key": 751, "value": 0.58}, "numberOfkeys": 1}, {"index": 39, "isLeaf": true, "children": [null, null, null, null], "items": {"key": 750, "value": 0.56}, "numberOfkeys": 1}, {"index": 40, "isLeaf": true, "children": [null, null, null, null], "items": {"key": 752, "value": 0.59}, "numberOfkeys": 1}, {"index": 41, "isLeaf": false, "children": [39, 40, 42, 43], "items": {"key": 753, "value": 0.62}, "numberOfkeys": 1}, {"index": 42, "isLeaf": true, "children": [null, null, null, null], "items": {"key": 754, "value": 0.66}, "numberOfkeys": 1}, {"index": 43, "isLeaf": true, "children": [null, null, null, null], "items": {"key": 756, "value": 0.71}, "numberOfkeys": 1}, {"index": 44, "isLeaf": false, "children": [42, 43, 46, 48], "items": {"key": 757, "value": 0.74}, "numberOfkeys": 1}, {"index": 45, "isLeaf": false, "children": [41, 44, 49, 52], "items": {"key": 759, "value": 0.78}, "numberOfkeys": 1}, {"index": 46, "isLeaf": true, "children": [null, null, null, null], "items": {"key": 758, "value": 0.76}, "numberOfkeys": 1}, {"index": 47, "isLeaf": false, "children": [38, 45, 53, 60], "items": {"key": 763, "value": 0.83}, "numberOfkeys": 1}, {"index": 48, "isLeaf": true, "children": [null, null, null, null], "items": {"key": 760, "value": 0.8}, "numberOfkeys": 1}, {"index": 49, "isLeaf": false, "children": [46, 48, 50, 51], "items": {"key": 761, "value": 0.81}, "numberOfkeys": 1}, {"index": 50, "isLeaf": true, "children": [null, null, null, null], "items": {"key": 762, "value": 0.82}, "numberOfkeys": 1}, {"index": 51, "isLeaf": true, "children": [null, null, null, null], "items": {"key": 764, "value": 0.86}, "numberOfkeys": 1}, {"index": 52, "isLeaf": false, "children": [50, 51, 54, 55], "items": {"key": 765, "value": 0.89}, "numberOfkeys": 1}, {"index": 53, "isLeaf": false, "children": [49, 52, 56, 59], "items": {"key": 767, "value": 0.94}, "numberOfkeys": 1}, {"index": 54, "isLeaf": true, "children": [null, null, null, null], "items": {"key": 766, "value": 0.92}, "numberOfkeys": 1}, {"index": 55, "isLeaf": true, "children": [null, null, null, null], "items": {"key": 768, "value": 0.95}, "numberOfkeys": 1}, {"index": 56, "isLeaf": false, "children": [54, 55, 57, 58], "items": {"key": 769, "value": 0.97}, "numberOfkeys": 1}, {"index": 57, "isLeaf": true, "children": [null, null, null, null], "items": {"key": 770, "value": 1.0}, "numberOfkeys": 1}, {"index": 58, "isLeaf": true, "children": [null, null, null, null], "items": {"key": 772, "value": 1.06}, "numberOfkeys": 1}, {"index": 59, "isLeaf": false, "children": [57, 58, 61, 65], "items": {"key": 773, "value": 1.07}, "numberOfkeys": 1}, {"index": 60, "isLeaf": false, "children": [56, 59, 66, 69], "items": {"key": 775, "value": 1.13}, "numberOfkeys": 1}, {"index": 61, "isLeaf": true, "children": [null, null, null, null], "items": {"key": 774, "value": 1.11}, "numberOfkeys": 1}, {"index": 62, "isLeaf": false, "children": [53, 60, 70, 77], "items": {"key": 779, "value": 1.25}, "numberOfkeys": 1}, {"index": 63, "isLeaf": false, "children": [31, 64, 95, 126], "items": {"key": 803, "value": 2.27}, "numberOfkeys": 1}, {"index": 64, "isLeaf": false, "children": [47, 62, 79, 94], "items": {"key": 787, "value": 1.61}, "numberOfkeys": 1}, {"index": 65, "isLeaf": true, "children": [null, null, null, null], "items": {"key": 776, "value": 1.16}, "numberOfkeys": 1}, {"index": 66, "isLeaf": false, "children": [61, 65, 67, 68], "items": {"key": 777, "value": 1.18}, "numberOfkeys": 1}, {"index": 67, "isLeaf": true, "children": [null, null, null, null], "items": {"key": 778, "value": 1.2}, "numberOfkeys": 1}, {"index": 68, "isLeaf": true, "children": [null, null, null, null], "items": {"key": 780, "value": 1.26}, "numberOfkeys": 1}, {"index": 69, "isLeaf": false, "children": [67, 68, 71, 72], "items": {"key": 781, "value": 1.3}, "numberOfkeys": 1}, {"index": 70, "isLeaf": false, "children": [66, 69, 73, 76], "items": {"key": 783, "value": 1.46}, "numberOfkeys": 1}, {"index": 71, "isLeaf": true, "children": [null, null, null, null], "items": {"key": 782, "value": 1.39}, "numberOfkeys": 1}, {"index": 72, "isLeaf": true, "children": [null, null, null, null], "items": {"key": 784, "value": 1.51}, "numberOfkeys": 1}, {"index": 73, "isLeaf": false, "children": [71, 72, 74, 75], "items": {"key": 785, "value": 1.54}, "numberOfkeys": 1}, {"index": 74, "isLeaf": true, "children": [null, null, null, null], "items": {"key": 786, "value": 1.58}, "numberOfkeys": 1}, {"index": 75, "isLeaf": true, "children": [null, null, null, null], "items": {"key": 788, "value": 1.65}, "numberOfkeys": 1}, {"index": 76, "isLeaf": false, "children": [74, 75, 78, 80], "items": {"key": 789, "value": 1.66}, "numberOfkeys": 1}, {"index": 77, "isLeaf": false, "children": [73, 76, 81, 84], "items": {"key": 791, "value": 1.78}, "numberOfkeys": 1}, {"index": 78, "isLeaf": true, "children": [null, null, null, null], "items": {"key": 790, "value": 1.72}, "numberOfkeys": 1}, {"index": 79, "isLeaf": false, "children": [70, 77, 85, 92], "items": {"key": 795, "value": 1.88}, "numberOfkeys": 1}, {"index": 80, "isLeaf": true, "children": [null, null, null, null], "items": {"key": 792, "value": 1.8}, "numberOfkeys": 1}, {"index": 81, "isLeaf": false, "children": [78, 80, 82, 83], "items": {"key": 793, "value": 1.83}, "numberOfkeys": 1}, {"index": 82, "isLeaf": true, "children": [null, null, null, null], "items": {"key": 794, "value": 1.85}, "numberOfkeys": 1}, {"index": 83, "isLeaf": true, "children": [null, null, null, null], "items": {"key": 796, "value": 1.92}, "numberOfkeys": 1}, {"index": 84, "isLeaf": false, "children": [82, 83, 86, 87], "items": {"key": 797, "value": 2.03}, "numberOfkeys": 1}, {"index": 85, "isLeaf": false, "children": [81, 84, 88, 91], "items": {"key": 799, "value": 2.14}, "numberOfkeys": 1}, {"index": 86, "isLeaf": true, "children": [null, null, null, null], "items": {"key": 798, "value": 2.1}, "numberOfkeys": 1}, {"index": 87, "isLeaf": true, "children": [null, null, null, null], "items": {"key": 800, "value": 2.18}, "numberOfkeys": 1}, {"index": 88, "isLeaf": false, "children": [86, 87, 89, 90], "items": {"key": 801, "value": 2.19}, "numberOfkeys": 1}, {"index": 89, "isLeaf": true, "children": [null, null, null, null], "items": {"key": 802, "value": 2.24}, "numberOfkeys": 1}, {"index": 90, "isLeaf": true, "children": [null, null, null, null], "items": {"key": 804, "value": 2.36}, "numberOfkeys": 1}, {"index": 91, "isLeaf": false, "children": [89, 90, 93, 96], "items": {"key": 805, "value": 2.38}, "numberOfkeys": 1}, {"index": 92, "isLeaf": false, "children": [88, 91, 97, 100], "items": {"key": 807, "value": 2.49}, "numberOfkeys": 1}, {"index": 93, "isLeaf": true, "children": [null, null, null, null], "items": {"key": 806, "value": 2.42}, "numberOfkeys": 1}, {"index": 94, "isLeaf": false, "children": [85, 92, 101, 108], "items": {"key": 811, "value": 2.78}, "numberOfkeys": 1}, {"index": 95, "isLeaf": false, "children": [79, 94, 110, 125], "items": {"key": 819, "value": 3.36}, "numberOfkeys": 1}, {"index": 96, "isLeaf": true, "children": [null, null, null, null], "items": {"key": 808, "value": 2.59}, "numberOfkeys": 1}, {"index": 97, "isLeaf": false, "children": [93, 96, 98, 99], "items": {"key": 809, "value": 2.68}, "numberOfkeys": 1}, {"index": 98, "isLeaf": true, "children": [null, null, null, null], "items": {"key": 810, "value": 2.73}, "numberOfkeys": 1}, {"index": 99, "isLeaf": true, "children": [null, null, null, null], "items": {"key": 812, "value": 2.86}, "numberOfkeys": 1}, {"index": 100, "isLeaf": false, "children": [98, 99, 102, 103], "items": {"key": 813, "value": 2.93}, "numberOfkeys": 1}, {"index": 101, "isLeaf": false, "children": [97, 100, 104, 107], "items": {"key": 815, "value": 3.1}, "numberOfkeys": 1}, {"index": 102, "isLeaf": true, "children": [null, null, null, null], "items": {"key": 814, "value": 3.04}, "numberOfkeys": 1}, {"index": 103, "isLeaf": true, "children": [null, null, null, null], "items": {"key": 816, "value": 3.18}, "numberOfkeys": 1}, {"index": 104, "isLeaf": false, "children": [102, 103, 105, 106], "items": {"key": 817, "value": 3.24}, "numberOfkeys": 1}, {"index": 105, "isLeaf": true, "children": [null, null, null, null], "items": {"key": 818, "value": 3.29}, "numberOfkeys": 1}, {"index": 106, "isLeaf": true, "children": [null, null, null, null], "items": {"key": 820, "value": 3.43}, "numberOfkeys": 1}, {"index": 107, "isLeaf": false, "children": [105, 106, 109, 111], "items": {"key": 821, "value": 3.54}, "numberOfkeys": 1}, {"index": 108, "isLeaf": false, "children": [104, 107, 112, 115], "items": {"key": 823, "value": 3.66}, "numberOfkeys": 1}, {"index": 109, "isLeaf": true, "children": [null, null, null, null], "items": {"key": 822, "value": 3.61}, "numberOfkeys": 1}, {"index": 110, "isLeaf": false, "children": [101, 108, 116, 123], "items": {"key": 827, "value": 4.13}, "numberOfkeys": 1}, {"index": 111, "isLeaf": true, "children": [null, null, null, null], "items": {"key": 824, "value": 3.81}, "numberOfkeys": 1}, {"index": 112, "isLeaf": false, "children": [109, 111, 113, 114], "items": {"key": 825, "value": 3.92}, "numberOfkeys": 1}, {"index": 113, "isLeaf": true, "children": [null, null, null, null], "items": {"key": 826, "value": 4.0}, "numberOfkeys": 1}, {"index": 114, "isLeaf": true, "children": [null, null, null, null], "items": {"key": 828, "value": 4.24}, "numberOfkeys": 1}, {"index": 115, "isLeaf": false, "children": [113, 114, 117, 118], "items": {"key": 829, "value": 4.31}, "numberOfkeys": 1}, {"index": 116, "isLeaf": false, "children": [112, 115, 119, 122], "items": {"key": 831, "value": 4.41}, "numberOfkeys": 1}, {"index": 117, "isLeaf": true, "children": [null, null, null, null], "items": {"key": 830, "value": 4.35}, "numberOfkeys": 1}, {"index": 118, "isLeaf": true, "children": [null, null, null, null], "items": {"key": 832, "value": 4.57}, "numberOfkeys": 1}, {"index": 119, "isLeaf": false, "children": [117, 118, 120, 121], "items": {"key": 833, "value": 4.67}, "numberOfkeys": 1}, {"index": 120, "isLeaf": true, "children": [null, null, null, null], "items": {"key": 834, "value": 4.8}, "numberOfkeys": 1}, {"index": 121, "isLeaf": true, "children": [null, null, null, null], "items": {"key": 836, "value": 4.98}, "numberOfkeys": 1}, {"index": 122, "isLeaf": false, "children": [120, 121, 124, 127], "items": {"key": 837, "value": 5.15}, "numberOfkeys": 1}, {"index": 123, "isLeaf": false, "children": [119, 122, 130, 133], "items": {"key": 839, "value": 5.3}, "numberOfkeys": 1}, {"index": 124, "isLeaf": true, "children": [null, null, null, null], "items": {"key": 838, "value": 5.23}, "numberOfkeys": 1}, {"index": 125, "isLeaf": false, "children": [116, 123, 134, 141], "items": {"key": 843, "value": 5.74}, "numberOfkeys": 1}, {"index": 126, "isLeaf": false, "children": [110, 125, 143, 158], "items": {"key": 851, "value": 6.75}, "numberOfkeys": 1}, {"index": 127, "isLeaf": true, "children": [null, null, null, null], "items": {"key": 840, "value": 5.36}, "numberOfkeys": 1}, {"index": 128, "isLeaf": false, "children": [63, 129, 192, 255], "items": {"key": 899, "value": 15.58}, "numberOfkeys": 1}, {"index": 129, "isLeaf": false, "children": [95, 126, 159, 190], "items": {"key": 867, "value": 9.35}, "numberOfkeys": 1}, {"index": 130, "isLeaf": false, "children": [124, 127, 131, 132], "items": {"key": 841, "value": 5.44}, "numberOfkeys": 1}, {"index": 131, "isLeaf": true, "children": [null, null, null, null], "items": {"key": 842, "value": 5.61}, "numberOfkeys": 1}, {"index": 132, "isLeaf": true, "children": [null, null, null, null], "items": {"key": 844, "value": 5.87}, "numberOfkeys": 1}, {"index": 133, "isLeaf": false, "children": [131, 132, 135, 136], "items": {"key": 845, "value": 5.99}, "numberOfkeys": 1}, {"index": 134, "isLeaf": false, "children": [130, 133, 137, 140], "items": {"key": 847, "value": 6.23}, "numberOfkeys": 1}, {"index": 135, "isLeaf": true, "children": [null, null, null, null], "items": {"key": 846, "value": 6.12}, "numberOfkeys": 1}, {"index": 136, "isLeaf": true, "children": [null, null, null, null], "items": {"key": 848, "value": 6.38}, "numberOfkeys": 1}, {"index": 137, "isLeaf": false, "children": [135, 136, 138, 139], "items": {"key": 849, "value": 6.52}, "numberOfkeys": 1}, {"index": 138, "isLeaf": true, "children": [null, null, null, null], "items": {"key": 850, "value": 6.62}, "numberOfkeys": 1}, {"index": 139, "isLeaf": true, "children": [null, null, null, null], "items": {"key": 852, "value": 6.83}, "numberOfkeys": 1}, {"index": 140, "isLeaf": false, "children": [138, 139, 142, 144], "items": {"key": 853, "value": 6.95}, "numberOfkeys": 1}, {"index": 141, "isLeaf": false, "children": [137, 140, 145, 148], "items": {"key": 855, "value": 7.2}, "numberOfkeys": 1}, {"index": 142, "isLeaf": true, "children": [null, null, null, null], "items": {"key": 854, "value": 7.08}, "numberOfkeys": 1}, {"index": 143, "isLeaf": false, "children": [134, 141, 149, 156], "items": {"key": 859, "value": 7.98}, "numberOfkeys": 1}, {"index": 144, "isLeaf": true, "children": [null, null, null, null], "items": {"key": 856, "value": 7.37}, "numberOfkeys": 1}, {"index": 145, "isLeaf": false, "children": [142, 144, 146, 147], "items": {"key": 857, "value": 7.62}, "numberOfkeys": 1}, {"index": 146, "isLeaf": true, "children": [null, null, null, null], "items": {"key": 858, "value": 7.8}, "numberOfkeys": 1}, {"index": 147, "isLeaf": true, "children": [null, null, null, null], "items": {"key": 860, "value": 8.17}, "numberOfkeys": 1}, {"index": 148, "isLeaf": false, "children": [146, 147, 150, 151], "items": {"key": 861, "value": 8.36}, "numberOfkeys": 1}, {"index": 149, "isLeaf": false, "children": [145, 148, 152, 155], "items": {"key": 863, "value": 8.66}, "numberOfkeys": 1}, {"index": 150, "isLeaf": true, "children": [null, null, null, null], "items": {"key": 862, "value": 8.53}, "numberOfkeys": 1}, {"index": 151, "isLeaf": true, "children": [null, null, null, null], "items": {"key": 864, "value": 8.78}, "numberOfkeys": 1}, {"index": 152, "isLeaf": false, "children": [150, 151, 153, 154], "items": {"key": 865, "value": 8.98}, "numberOfkeys": 1}, {"index": 153, "isLeaf": true, "children": [null, null, null, null], "items": {"key": 866, "value": 9.17}, "numberOfkeys": 1}, {"index": 154, "isLeaf": true, "children": [null, null, null, null], "items": {"key": 868, "value": 9.48}, "numberOfkeys": 1}, {"index": 155, "isLeaf": false, "children": [153, 154, 157, 160], "items": {"key": 869, "value": 9.64}, "numberOfkeys": 1}, {"index": 156, "isLeaf": false, "children": [152, 155, 161, 164], "items": {"key": 871, "value": 9.95}, "numberOfkeys": 1}, {"index": 157, "isLeaf": true, "children": [null, null, null, null], "items": {"key": 870, "value": 9.79}, "numberOfkeys": 1}, {"index": 158, "isLeaf": false, "children": [149, 156, 165, 172], "items": {"key": 875, "value": 10.62}, "numberOfkeys": 1}, {"index": 159, "isLeaf": false, "children": [143, 158, 174, 189], "items": {"key": 883, "value": 12.01}, "numberOfkeys": 1}, {"index": 160, "isLeaf": true, "children": [null, null, null, null], "items": {"key": 872, "value": 10.08}, "numberOfkeys": 1}, {"index": 161, "isLeaf": false, "children": [157, 160, 162, 163], "items": {"key": 873, "value": 10.24}, "numberOfkeys": 1}, {"index": 162, "isLeaf": true, "children": [null, null, null, null], "items": {"key": 874, "value": 10.43}, "numberOfkeys": 1}, {"index": 163, "isLeaf": true, "children": [null, null, null, null], "items": {"key": 876, "value": 10.8}, "numberOfkeys": 1}, {"index": 164, "isLeaf": false, "children": [162, 163, 166, 167], "items": {"key": 877, "value": 10.97}, "numberOfkeys": 1}, {"index": 165, "isLeaf": false, "children": [161, 164, 168, 171], "items": {"key": 879, "value": 11.28}, "numberOfkeys": 1}, {"index": 166, "isLeaf": true, "children": [null, null, null, null], "items": {"key": 878, "value": 11.18}, "numberOfkeys": 1}, {"index": 167, "isLeaf": true, "children": [null, null, null, null], "items": {"key": 880, "value": 11.47}, "numberOfkeys": 1}, {"index": 168, "isLeaf": false, "children": [166, 167, 169, 170], "items": {"key": 881, "value": 11.66}, "numberOfkeys": 1}, {"index": 169, "isLeaf": true, "children": [null, null, null, null], "items": {"key": 882, "value": 11.81}, "numberOfkeys": 1}, {"index": 170, "isLeaf": true, "children": [null, null, null, null], "items": {"key": 884, "value": 12.27}, "numberOfkeys": 1}, {"index": 171, "isLeaf": false, "children": [169, 170, 173, 175], "items": {"key": 885, "value": 12.47}, "numberOfkeys": 1}, {"index": 172, "isLeaf": false, "children": [168, 171, 176, 179], "items": {"key": 887, "value": 12.86}, "numberOfkeys": 1}, {"index": 173, "isLeaf": true, "children": [null, null, null, null], "items": {"key": 886, "value": 12.69}, "numberOfkeys": 1}, {"index": 174, "isLeaf": false, "children": [165, 172, 180, 187], "items": {"key": 891, "value": 13.75}, "numberOfkeys": 1}, {"index": 175, "isLeaf": true, "children": [null, null, null, null], "items": {"key": 888, "value": 13.13}, "numberOfkeys": 1}, {"index": 176, "isLeaf": false, "children": [173, 175, 177, 178], "items": {"key": 889, "value": 13.32}, "numberOfkeys": 1}, {"index": 177, "isLeaf": true, "children": [null, null, null, null], "items": {"key": 890, "value": 13.51}, "numberOfkeys": 1}, {"index": 178, "isLeaf": true, "children": [null, null, null, null], "items": {"key": 892, "value": 13.94}, "numberOfkeys": 1}, {"index": 179, "isLeaf": false, "children": [177, 178, 181, 182], "items": {"key": 893, "value": 14.19}, "numberOfkeys": 1}, {"index": 180, "isLeaf": false, "children": [176, 179, 183, 186], "items": {"key": 895, "value": 14.7}, "numberOfkeys": 1}, {"index": 181, "isLeaf": true, "children": [null, null, null, null], "items": {"key": 894, "value": 14.43}, "numberOfkeys": 1}, {"index": 182, "isLeaf": true, "children": [null, null, null, null], "items": {"key": 896, "value": 14.94}, "numberOfkeys": 1}, {"index": 183, "isLeaf": false, "children": [181, 182, 184, 185], "items": {"key": 897, "value": 15.14}, "numberOfkeys": 1}, {"index": 184, "isLeaf": true, "children": [null, null, null, null], "items": {"key": 898, "value": 15.4}, "numberOfkeys": 1}, {"index": 185, "isLeaf": true, "children": [null, null, null, null], "items": {"key": 900, "value": 15.83}, "numberOfkeys": 1}, {"index": 186, "isLeaf": false, "children": [184, 185, 188, 191], "items": {"key": 901, "value": 16.04}, "numberOfkeys": 1}, {"index": 187, "isLeaf": false, "children": [183, 186, 193, 196], "items": {"key": 903, "value": 16.64}, "numberOfkeys": 1}, {"index": 188, "isLeaf": true, "children": [null, null, null, null], "items": {"key": 902, "value": 16.28}, "numberOfkeys": 1}, {"index": 189, "isLeaf": false, "children": [180, 187, 197, 204], "items": {"key": 907, "value": 17.7}, "numberOfkeys": 1}, {"index": 190, "isLeaf": false, "children": [174, 189, 206, 221], "items": {"key": 915, "value": 19.63}, "numberOfkeys": 1}, {"index": 191, "isLeaf": true, "children": [null, null, null, null], "items": {"key": 904, "value": 16.91}, "numberOfkeys": 1}, {"index": 192, "isLeaf": false, "children": [159, 190, 222, 253], "items": {"key": 931, "value": 24.35}, "numberOfkeys": 1}, {"index": 193, "isLeaf": false, "children": [188, 191, 194, 195], "items": {"key": 905, "value": 17.18}, "numberOfkeys": 1}, {"index": 194, "isLeaf": true, "children": [null, null, null, null], "items": {"key": 906, "value": 17.5}, "numberOfkeys": 1}, {"index": 195, "isLeaf": true, "children": [null, null, null, null], "items": {"key": 908, "value": 17.94}, "numberOfkeys": 1}, {"index": 196, "isLeaf": false, "children": [194, 195, 198, 199], "items": {"key": 909, "value": 18.22}, "numberOfkeys": 1}, {"index": 197, "isLeaf": false, "children": [193, 196, 200, 203], "items": {"key": 911, "value": 18.72}, "numberOfkeys": 1}, {"index": 198, "isLeaf": true, "children": [null, null, null, null], "items": {"key": 910, "value": 18.48}, "numberOfkeys": 1}, {"index": 199, "isLeaf": true, "children": [null, null, null, null], "items": {"key": 912, "value": 18.97}, "numberOfkeys": 1}, {"index": 200, "isLeaf": false, "children": [198, 199, 201, 202], "items": {"key": 913, "value": 19.2}, "numberOfkeys": 1}, {"index": 201, "isLeaf": true, "children": [null, null, null, null], "items": {"key": 914, "value": 19.4}, "numberOfkeys": 1}, {"index": 202, "isLeaf": true, "children": [null, null, null, null], "items": {"key": 916, "value": 19.94}, "numberOfkeys": 1}, {"index": 203, "isLeaf": false, "children": [201, 202, 205, 207], "items": {"key": 917, "value": 20.25}, "numberOfkeys": 1}, {"index": 204, "isLeaf": false, "children": [200, 203, 208, 211], "items": {"key": 919, "value": 20.79}, "numberOfkeys": 1}, {"index": 205, "isLeaf": true, "children": [null, null, null, null], "items": {"key": 918, "value": 20.51}, "numberOfkeys": 1}, {"index": 206, "isLeaf": false, "children": [197, 204, 212, 219], "items": {"key": 923, "value": 21.96}, "numberOfkeys": 1}, {"index": 207, "isLeaf": true, "children": [null, null, null, null], "items": {"key": 920, "value": 21.11}, "numberOfkeys": 1}, {"index": 208, "isLeaf": false, "children": [205, 207, 209, 210], "items": {"key": 921, "value": 21.45}, "numberOfkeys": 1}, {"index": 209, "isLeaf": true, "children": [null, null, null, null], "items": {"key": 922, "value": 21.77}, "numberOfkeys": 1}, {"index": 210, "isLeaf": true, "children": [null, null, null, null], "items": {"key": 924, "value": 22.25}, "numberOfkeys": 1}, {"index": 211, "isLeaf": false, "children": [209, 210, 213, 214], "items": {"key": 925, "value": 22.52}, "numberOfkeys": 1}, {"index": 212, "isLeaf": false, "children": [208, 211, 215, 218], "items": {"key": 927, "value": 23.1}, "numberOfkeys": 1}, {"index": 213, "isLeaf": true, "children": [null, null, null, null], "items": {"key": 926, "value": 22.77}, "numberOfkeys": 1}, {"index": 214, "isLeaf": true, "children": [null, null, null, null], "items": {"key": 928, "value": 23.47}, "numberOfkeys": 1}, {"index": 215, "isLeaf": false, "children": [213, 214, 216, 217], "items": {"key": 929, "value": 23.74}, "numberOfkeys": 1}, {"index": 216, "isLeaf": true, "children": [null, null, null, null], "items": {"key": 930, "value": 24.02}, "numberOfkeys": 1}, {"index": 217, "isLeaf": true, "children": [null, null, null, null], "items": {"key": 932, "value": 24.69}, "numberOfkeys": 1}, {"index": 218, "isLeaf": false, "children": [216, 217, 220, 223], "items": {"key": 933, "value": 24.99}, "numberOfkeys": 1}, {"index": 219, "isLeaf": false, "children": [215, 218, 224, 227], "items": {"key": 935, "value": 25.56}, "numberOfkeys": 1}, {"index": 220, "isLeaf": true, "children": [null, null, null, null], "items": {"key": 934, "value": 25.26}, "numberOfkeys": 1}, {"index": 221, "isLeaf": false, "children": [212, 219, 228, 235], "items": {"key": 939, "value": 26.64}, "numberOfkeys": 1}, {"index": 222, "isLeaf": false, "children": [206, 221, 237, 252], "items": {"key": 947, "value": 29.49}, "numberOfkeys": 1}, {"index": 223, "isLeaf": true, "children": [null, null, null, null], "items": {"key": 936, "value": 25.86}, "numberOfkeys": 1}, {"index": 224, "isLeaf": false, "children": [220, 223, 225, 226], "items": {"key": 937, "value": 26.09}, "numberOfkeys": 1}, {"index": 225, "isLeaf": true, "children": [null, null, null, null], "items": {"key": 938, "value": 26.41}, "numberOfkeys": 1}, {"index": 226, "isLeaf": true, "children": [null, null, null, null], "items": {"key": 940, "value": 26.97}, "numberOfkeys": 1}, {"index": 227, "isLeaf": false, "children": [225, 226, 229, 230], "items": {"key": 941, "value": 27.33}, "numberOfkeys": 1}, {"index": 228, "isLeaf": false, "children": [224, 227, 231, 234], "items": {"key": 943, "value": 28.0}, "numberOfkeys": 1}, {"index": 229, "isLeaf": true, "children": [null, null, null, null], "items": {"key": 942, "value": 27.68}, "numberOfkeys": 1}, {"index": 230, "isLeaf": true, "children": [null, null, null, null], "items": {"key": 944, "value": 28.35}, "numberOfkeys": 1}, {"index": 231, "isLeaf": false, "children": [229, 230, 232, 233], "items": {"key": 945, "value": 28.67}, "numberOfkeys": 1}, {"index": 232, "isLeaf": true, "children": [null, null, null, null], "items": {"key": 946, "value": 29.11}, "numberOfkeys": 1}, {"index": 233, "isLeaf": true, "children": [null, null, null, null], "items": {"key": 948, "value": 29.93}, "numberOfkeys": 1}, {"index": 234, "isLeaf": false, "children": [232, 233, 236, 238], "items": {"key": 949, "value": 30.26}, "numberOfkeys": 1}, {"index": 235, "isLeaf": false, "children": [231, 234, 239, 242], "items": {"key": 951, "value": 31.03}, "numberOfkeys": 1}, {"index": 236, "isLeaf": true, "children": [null, null, null, null], "items": {"key": 950, "value": 30.67}, "numberOfkeys": 1}, {"index": 237, "isLeaf": false, "children": [228, 235, 243, 250], "items": {"key": 955, "value": 32.46}, "numberOfkeys": 1}, {"index": 238, "isLeaf": true, "children": [null, null, null, null], "items": {"key": 952, "value": 31.42}, "numberOfkeys": 1}, {"index": 239, "isLeaf": false, "children": [236, 238, 240, 241], "items": {"key": 953, "value": 31.79}, "numberOfkeys": 1}, {"index": 240, "isLeaf": true, "children": [null, null, null, null], "items": {"key": 954, "value": 32.1}, "numberOfkeys": 1}, {"index": 241, "isLeaf": true, "children": [null, null, null, null], "items": {"key": 956, "value": 32.82}, "numberOfkeys": 1}, {"index": 242, "isLeaf": false, "children": [240, 241, 244, 245], "items": {"key": 957, "value": 33.15}, "numberOfkeys": 1}, {"index": 243, "isLeaf": false, "children": [239, 242, 246, 249], "items": {"key": 959, "value": 33.82}, "numberOfkeys": 1}, {"index": 244, "isLeaf": true, "children": [null, null, null, null], "items": {"key": 958, "value": 33.46}, "numberOfkeys": 1}, {"index": 245, "isLeaf": true, "children": [null, null, null, null], "items": {"key": 960, "value": 34.19}, "numberOfkeys": 1}, {"index": 246, "isLeaf": false, "children": [244, 245, 247, 248], "items": {"key": 961, "value": 34.46}, "numberOfkeys": 1}, {"index": 247, "isLeaf": true, "children": [null, null, null, null], "items": {"key": 962, "value": 34.79}, "numberOfkeys": 1}, {"index": 248, "isLeaf": true, "children": [null, null, null, null], "items": {"key": 964, "value": 35.48}, "numberOfkeys": 1}, {"index": 249, "isLeaf": false, "children": [247, 248, 251, 254], "items": {"key": 965, "value": 35.81}, "numberOfkeys": 1}, {"index": 250, "isLeaf": false, "children": [246, 249, 256, 261], "items": {"key": 967, "value": 36.45}, "numberOfkeys": 1}, {"index": 251, "isLeaf": true, "children": [null, null, null, null], "items": {"key": 966, "value": 36.17}, "numberOfkeys": 1}, {"index": 252, "isLeaf": false, "children": [243, 250, 262, 269], "items": {"key": 971, "value": 38.09}, "numberOfkeys": 1}, {"index": 253, "isLeaf": false, "children": [237, 252, 271, 286], "items": {"key": 979, "value": 41.15}, "numberOfkeys": 1}, {"index": 254, "isLeaf": true, "children": [null, null, null, null], "items": {"key": 968, "value": 36.96}, "numberOfkeys": 1}, {"index": 255, "isLeaf": false, "children": [222, 253, 287, 318], "items": {"key": 995, "value": 47.18}, "numberOfkeys": 1}, {"index": 256, "isLeaf": false, "children": [251, 254, 259, 260], "items": {"key": 969, "value": 37.36}, "numberOfkeys": 1}, {"index": 257, "isLeaf": false, "children": [128, 258, 385, 512], "items": {"key": 1091, "value": 81.17}, "numberOfkeys": 1}, {"index": 258, "isLeaf": false, "children": [192, 255, 320, 383], "items": {"key": 1027, "value": 59.74}, "numberOfkeys": 1}, {"index": 259, "isLeaf": true, "children": [null, null, null, null], "items": {"key": 970, "value": 37.7}, "numberOfkeys": 1}, {"index": 260, "isLeaf": true, "children": [null, null, null, null], "items": {"key": 972, "value": 38.39}, "numberOfkeys": 1}, {"index": 261, "isLeaf": false, "children": [259, 260, 263, 264], "items": {"key": 973, "value": 38.79}, "numberOfkeys": 1}, {"index": 262, "isLeaf": false, "children": [256, 261, 265, 268], "items": {"key": 975, "value": 39.52}, "numberOfkeys": 1}, {"index": 263, "isLeaf": true, "children": [null, null, null, null], "items": {"key": 974, "value": 39.18}, "numberOfkeys": 1}, {"index": 264, "isLeaf": true, "children": [null, null, null, null], "items": {"key": 976, "value": 39.88}, "numberOfkeys": 1}, {"index": 265, "isLeaf": false, "children": [263, 264, 266, 267], "items": {"key": 977, "value": 40.33}, "numberOfkeys": 1}, {"index": 266, "isLeaf": true, "children": [null, null, null, null], "items": {"key": 978, "value": 40.73}, "numberOfkeys": 1}, {"index": 267, "isLeaf": true, "children": [null, null, null, null], "items": {"key": 980, "value": 41.56}, "numberOfkeys": 1}, {"index": 268, "isLeaf": false, "children": [266, 267, 270, 272], "items": {"key": 981, "value": 41.96}, "numberOfkeys": 1}, {"index": 269, "isLeaf": false, "children": [265, 268, 273, 276], "items": {"key": 983, "value": 42.64}, "numberOfkeys": 1}, {"index": 270, "isLeaf": true, "children": [null, null, null, null], "items": {"key": 982, "value": 42.29}, "numberOfkeys": 1}, {"index": 271, "isLeaf": false, "children": [262, 269, 277, 284], "items": {"key": 987, "value": 44.2}, "numberOfkeys": 1}, {"index": 272, "isLeaf": true, "children": [null, null, null, null], "items": {"key": 984, "value": 43.02}, "numberOfkeys": 1}, {"index": 273, "isLeaf": false, "children": [270, 272, 274, 275], "items": {"key": 985, "value": 43.43}, "numberOfkeys": 1}, {"index": 274, "isLeaf": true, "children": [null, null, null, null], "items": {"key": 986, "value": 43.84}, "numberOfkeys": 1}, {"index": 275, "isLeaf": true, "children": [null, null, null, null], "items": {"key": 988, "value": 44.64}, "numberOfkeys": 1}, {"index": 276, "isLeaf": false, "children": [274, 275, 278, 279], "items": {"key": 989, "value": 44.86}, "numberOfkeys": 1}, {"index": 277, "isLeaf": false, "children": [273, 276, 280, 283], "items": {"key": 991, "value": 45.63}, "numberOfkeys": 1}, {"index": 278, "isLeaf": true, "children": [null, null, null, null], "items": {"key": 990, "value": 45.23}, "numberOfkeys": 1}, {"index": 279, "isLeaf": true, "children": [null, null, null, null], "items": {"key": 992, "value": 46.01}, "numberOfkeys": 1}, {"index": 280, "isLeaf": false, "children": [278, 279, 281, 282], "items": {"key": 993, "value": 46.43}, "numberOfkeys": 1}, {"index": 281, "isLeaf": true, "children": [null, null, null, null], "items": {"key": 994, "value": 46.82}, "numberOfkeys": 1}, {"index": 282, "isLeaf": true, "children": [null, null, null, null], "items": {"key": 996, "value": 47.55}, "numberOfkeys": 1}, {"index": 283, "isLeaf": false, "children": [281, 282, 285, 288], "items": {"key": 997, "value": 48.08}, "numberOfkeys": 1}, {"index": 284, "isLeaf": false, "children": [280, 283, 289, 292], "items": {"key": 999, "value": 48.87}, "numberOfkeys": 1}, {"index": 285, "isLeaf": true, "children": [null, null, null, null], "items": {"key": 998, "value": 48.45}, "numberOfkeys": 1}, {"index": 286, "isLeaf": false, "children": [277, 284, 293, 300], "items": {"key": 1003, "value": 50.46}, "numberOfkeys": 1}, {"index": 287, "isLeaf": false, "children": [271, 286, 302, 317], "items": {"key": 1011, "value": 53.53}, "numberOfkeys": 1}, {"index": 288, "isLeaf": true, "children": [null, null, null, null], "items": {"key": 1000, "value": 49.23}, "numberOfkeys": 1}, {"index": 289, "isLeaf": false, "children": [285, 288, 290, 291], "items": {"key": 1001, "value": 49.69}, "numberOfkeys": 1}, {"index": 290, "isLeaf": true, "children": [null, null, null, null], "items": {"key": 1002, "value": 50.13}, "numberOfkeys": 1}, {"index": 291, "isLeaf": true, "children": [null, null, null, null], "items": {"key": 1004, "value": 50.85}, "numberOfkeys": 1}, {"index": 292, "isLeaf": false, "children": [290, 291, 294, 295], "items": {"key": 1005, "value": 51.24}, "numberOfkeys": 1}, {"index": 293, "isLeaf": false, "children": [289, 292, 296, 299], "items": {"key": 1007, "value": 51.86}, "numberOfkeys": 1}, {"index": 294, "isLeaf": true, "children": [null, null, null, null], "items": {"key": 1006, "value": 51.57}, "numberOfkeys": 1}, {"index": 295, "isLeaf": true, "children": [null, null, null, null], "items": {"key": 1008, "value": 52.24}, "numberOfkeys": 1}, {"index": 296, "isLeaf": false, "children": [294, 295, 297, 298], "items": {"key": 1009, "value": 52.68}, "numberOfkeys": 1}, {"index": 297, "isLeaf": true, "children": [null, null, null, null], "items": {"key": 1010, "value": 53.12}, "numberOfkeys": 1}, {"index": 298, "isLeaf": true, "children": [null, null, null, null], "items": {"key": 1012, "value": 53.92}, "numberOfkeys": 1}, {"index": 299, "isLeaf": false, "children": [297, 298, 301, 303], "items": {"key": 1013, "value": 54.34}, "numberOfkeys": 1}, {"index": 300, "isLeaf": false, "children": [296, 299, 304, 307], "items": {"key": 1015, "value": 55.29}, "numberOfkeys": 1}, {"index": 301, "isLeaf": true, "children": [null, null, null, null], "items": {"key": 1014, "value": 54.8}, "numberOfkeys": 1}, {"index": 302, "isLeaf": false, "children": [293, 300, 308, 315], "items": {"key": 1019, "value": 56.91}, "numberOfkeys": 1}, {"index": 303, "isLeaf": true, "children": [null, null, null, null], "items": {"key": 1016, "value": 55.72}, "numberOfkeys": 1}, {"index": 304, "isLeaf": false, "children": [301, 303, 305, 306], "items": {"key": 1017, "value": 56.21}, "numberOfkeys": 1}, {"index": 305, "isLeaf": true, "children": [null, null, null, null], "items": {"key": 1018, "value": 56.58}, "numberOfkeys": 1}, {"index": 306, "isLeaf": true, "children": [null, null, null, null], "items": {"key": 1020, "value": 57.3}, "numberOfkeys": 1}, {"index": 307, "isLeaf": false, "children": [305, 306, 309, 310], "items": {"key": 1021, "value": 57.66}, "numberOfkeys": 1}, {"index": 308, "isLeaf": false, "children": [304, 307, 311, 314], "items": {"key": 1023, "value": 58.48}, "numberOfkeys": 1}, {"index": 309, "isLeaf": true, "children": [null, null, null, null], "items": {"key": 1022, "value": 58.0}, "numberOfkeys": 1}, {"index": 310, "isLeaf": true, "children": [null, null, null, null], "items": {"key": 1024, "value": 58.82}, "numberOfkeys": 1}, {"index": 311, "isLeaf": false, "children": [309, 310, 312, 313], "items": {"key": 1025, "value": 59.15}, "numberOfkeys": 1}, {"index": 312, "isLeaf": true, "children": [null, null, null, null], "items": {"key": 1026, "value": 59.49}, "numberOfkeys": 1}, {"index": 313, "isLeaf": true, "children": [null, null, null, null], "items": {"key": 1028, "value": 60.2}, "numberOfkeys": 1}, {"index": 314, "isLeaf": false, "children": [312, 313, 316, 319], "items": {"key": 1029, "value": 60.61}, "numberOfkeys": 1}, {"index": 315, "isLeaf": false, "children": [311, 314, 321, 324], "items": {"key": 1031, "value": 61.39}, "numberOfkeys": 1}, {"index": 316, "isLeaf": true, "children": [null, null, null, null], "items": {"key": 1030, "value": 61.02}, "numberOfkeys": 1}, {"index": 317, "isLeaf": false, "children": [308, 315, 325, 332], "items": {"key": 1035, "value": 63.09}, "numberOfkeys": 1}, {"index": 318, "isLeaf": false, "children": [302, 317, 334, 349], "items": {"key": 1043, "value": 66.14}, "numberOfkeys": 1}, {"index": 319, "isLeaf": true, "children": [null, null, null, null], "items": {"key": 1032, "value": 61.85}, "numberOfkeys": 1}, {"index": 320, "isLeaf": false, "children": [287, 318, 350, 381], "items": {"key": 1059, "value": 71.5}, "numberOfkeys": 1}, {"index": 321, "isLeaf": false, "children": [316, 319, 322, 323], "items": {"key": 1033, "value": 62.29}, "numberOfkeys": 1}, {"index": 322, "isLeaf": true, "children": [null, null, null, null], "items": {"key": 1034, "value": 62.69}, "numberOfkeys": 1}, {"index": 323, "isLeaf": true, "children": [null, null, null, null], "items": {"key": 1036, "value": 63.43}, "numberOfkeys": 1}, {"index": 324, "isLeaf": false, "children": [322, 323, 326, 327], "items": {"key": 1037, "value": 63.87}, "numberOfkeys": 1}, {"index": 325, "isLeaf": false, "children": [321, 324, 328, 331], "items": {"key": 1039, "value": 64.57}, "numberOfkeys": 1}, {"index": 326, "isLeaf": true, "children": [null, null, null, null], "items": {"key": 1038, "value": 64.25}, "numberOfkeys": 1}, {"index": 327, "isLeaf": true, "children": [null, null, null, null], "items": {"key": 1040, "value": 64.99}, "numberOfkeys": 1}, {"index": 328, "isLeaf": false, "children": [326, 327, 329, 330], "items": {"key": 1041, "value": 65.39}, "numberOfkeys": 1}, {"index": 329, "isLeaf": true, "children": [null, null, null, null], "items": {"key": 1042, "value": 65.79}, "numberOfkeys": 1}, {"index": 330, "isLeaf": true, "children": [null, null, null, null], "items": {"key": 1044, "value": 66.46}, "numberOfkeys": 1}, {"index": 331, "isLeaf": false, "children": [329, 330, 333, 335], "items": {"key": 1045, "value": 66.86}, "numberOfkeys": 1}, {"index": 332, "isLeaf": false, "children": [328, 331, 336, 339], "items": {"key": 1047, "value": 67.4}, "numberOfkeys": 1}, {"index": 333, "isLeaf": true, "children": [null, null, null, null], "items": {"key": 1046, "value": 67.16}, "numberOfkeys": 1}, {"index": 334, "isLeaf": false, "children": [325, 332, 340, 347], "items": {"key": 1051, "value": 68.61}, "numberOfkeys": 1}, {"index": 335, "isLeaf": true, "children": [null, null, null, null], "items": {"key": 1048, "value": 67.8}, "numberOfkeys": 1}, {"index": 336, "isLeaf": false, "children": [333, 335, 337, 338], "items": {"key": 1049, "value": 68.09}, "numberOfkeys": 1}, {"index": 337, "isLeaf": true, "children": [null, null, null, null], "items": {"key": 1050, "value": 68.34}, "numberOfkeys": 1}, {"index": 338, "isLeaf": true, "children": [null, null, null, null], "items": {"key": 1052, "value": 68.98}, "numberOfkeys": 1}, {"index": 339, "isLeaf": false, "children": [337, 338, 341, 342], "items": {"key": 1053, "value": 69.41}, "numberOfkeys": 1}, {"index": 340, "isLeaf": false, "children": [336, 339, 343, 346], "items": {"key": 1055, "value": 70.23}, "numberOfkeys": 1}, {"index": 341, "isLeaf": true, "children": [null, null, null, null], "items": {"key": 1054, "value": 69.85}, "numberOfkeys": 1}, {"index": 342, "isLeaf": true, "children": [null, null, null, null], "items": {"key": 1056, "value": 70.47}, "numberOfkeys": 1}, {"index": 343, "isLeaf": false, "children": [341, 342, 344, 345], "items": {"key": 1057, "value": 70.78}, "numberOfkeys": 1}, {"index": 344, "isLeaf": true, "children": [null, null, null, null], "items": {"key": 1058, "value": 71.09}, "numberOfkeys": 1}, {"index": 345, "isLeaf": true, "children": [null, null, null, null], "items": {"key": 1060, "value": 71.79}, "numberOfkeys": 1}, {"index": 346, "isLeaf": false, "children": [344, 345, 348, 351], "items": {"key": 1061, "value": 72.09}, "numberOfkeys": 1}, {"index": 347, "isLeaf": false, "children": [343, 346, 352, 355], "items": {"key": 1063, "value": 72.59}, "numberOfkeys": 1}, {"index": 348, "isLeaf": true, "children": [null, null, null, null], "items": {"key": 1062, "value": 72.31}, "numberOfkeys": 1}, {"index": 349, "isLeaf": false, "children": [340, 347, 356, 363], "items": {"key": 1067, "value": 73.79}, "numberOfkeys": 1}, {"index": 350, "isLeaf": false, "children": [334, 349, 365, 380], "items": {"key": 1075, "value": 76.4}, "numberOfkeys": 1}, {"index": 351, "isLeaf": true, "children": [null, null, null, null], "items": {"key": 1064, "value": 72.84}, "numberOfkeys": 1}, {"index": 352, "isLeaf": false, "children": [348, 351, 353, 354], "items": {"key": 1065, "value": 73.14}, "numberOfkeys": 1}, {"index": 353, "isLeaf": true, "children": [null, null, null, null], "items": {"key": 1066, "value": 73.48}, "numberOfkeys": 1}, {"index": 354, "isLeaf": true, "children": [null, null, null, null], "items": {"key": 1068, "value": 74.22}, "numberOfkeys": 1}, {"index": 355, "isLeaf": false, "children": [353, 354, 357, 358], "items": {"key": 1069, "value": 74.56}, "numberOfkeys": 1}, {"index": 356, "isLeaf": false, "children": [352, 355, 359, 362], "items": {"key": 1071, "value": 75.14}, "numberOfkeys": 1}, {"index": 357, "isLeaf": true, "children": [null, null, null, null], "items": {"key": 1070, "value": 74.92}, "numberOfkeys": 1}, {"index": 358, "isLeaf": true, "children": [null, null, null, null], "items": {"key": 1072, "value": 75.47}, "numberOfkeys": 1}, {"index": 359, "isLeaf": false, "children": [357, 358, 360, 361], "items": {"key": 1073, "value": 75.77}, "numberOfkeys": 1}, {"index": 360, "isLeaf": true, "children": [null, null, null, null], "items": {"key": 1074, "value": 76.05}, "numberOfkeys": 1}, {"index": 361, "isLeaf": true, "children": [null, null, null, null], "items": {"key": 1076, "value": 76.69}, "numberOfkeys": 1}, {"index": 362, "isLeaf": false, "children": [360, 361, 364, 366], "items": {"key": 1077, "value": 76.96}, "numberOfkeys": 1}, {"index": 363, "isLeaf": false, "children": [359, 362, 367, 370], "items": {"key": 1079, "value": 77.66}, "numberOfkeys": 1}, {"index": 364, "isLeaf": true, "children": [null, null, null, null], "items": {"key": 1078, "value": 77.21}, "numberOfkeys": 1}, {"index": 365, "isLeaf": false, "children": [356, 363, 371, 378], "items": {"key": 1083, "value": 78.94}, "numberOfkeys": 1}, {"index": 366, "isLeaf": true, "children": [null, null, null, null], "items": {"key": 1080, "value": 78.03}, "numberOfkeys": 1}, {"index": 367, "isLeaf": false, "children": [364, 366, 368, 369], "items": {"key": 1081, "value": 78.35}, "numberOfkeys": 1}, {"index": 368, "isLeaf": true, "children": [null, null, null, null], "items": {"key": 1082, "value": 78.68}, "numberOfkeys": 1}, {"index": 369, "isLeaf": true, "children": [null, null, null, null], "items": {"key": 1084, "value": 79.23}, "numberOfkeys": 1}, {"index": 370, "isLeaf": false, "children": [368, 369, 372, 373], "items": {"key": 1085, "value": 79.47}, "numberOfkeys": 1}, {"index": 371, "isLeaf": false, "children": [367, 370, 374, 377], "items": {"key": 1087, "value": 80.01}, "numberOfkeys": 1}, {"index": 372, "isLeaf": true, "children": [null, null, null, null], "items": {"key": 1086, "value": 79.76}, "numberOfkeys": 1}, {"index": 373, "isLeaf": true, "children": [null, null, null, null], "items": {"key": 1088, "value": 80.26}, "numberOfkeys": 1}, {"index": 374, "isLeaf": false, "children": [372, 373, 375, 376], "items": {"key": 1089, "value": 80.58}, "numberOfkeys": 1}, {"index": 375, "isLeaf": true, "children": [null, null, null, null], "items": {"key": 1090, "value": 80.85}, "numberOfkeys": 1}, {"index": 376, "isLeaf": true, "children": [null, null, null, null], "items": {"key": 1092, "value": 81.54}, "numberOfkeys": 1}, {"index": 377, "isLeaf": false, "children": [375, 376, 379, 382], "items": {"key": 1093, "value": 81.79}, "numberOfkeys": 1}, {"index": 378, "isLeaf": false, "children": [374, 377, 384, 388], "items": {"key": 1095, "value": 82.32}, "numberOfkeys": 1}, {"index": 379, "isLeaf": true, "children": [null, null, null, null], "items": {"key": 1094, "value": 81.99}, "numberOfkeys": 1}, {"index": 380, "isLeaf": false, "children": [371, 378, 389, 396], "items": {"key": 1099, "value": 83.35}, "numberOfkeys": 1}, {"index": 381, "isLeaf": false, "children": [365, 380, 398, 413], "items": {"key": 1107, "value": 85.53}, "numberOfkeys": 1}, {"index": 382, "isLeaf": true, "children": [null, null, null, null], "items": {"key": 1096, "value": 82.55}, "numberOfkeys": 1}, {"index": 383, "isLeaf": false, "children": [350, 381, 414, 445], "items": {"key": 1123, "value": 88.71}, "numberOfkeys": 1}, {"index": 384, "isLeaf": false, "children": [379, 382, 386, 387], "items": {"key": 1097, "value": 82.87}, "numberOfkeys": 1}, {"index": 385, "isLeaf": false, "children": [320, 383, 447, 510], "items": {"key": 1155, "value": 93.65}, "numberOfkeys": 1}, {"index": 386, "isLeaf": true, "children": [null, null, null, null], "items": {"key": 1098, "value": 83.06}, "numberOfkeys": 1}, {"index": 387, "isLeaf": true, "children": [null, null, null, null], "items": {"key": 1100, "value": 83.59}, "numberOfkeys": 1}, {"index": 388, "isLeaf": false, "children": [386, 387, 390, 391], "items": {"key": 1101, "value": 83.8}, "numberOfkeys": 1}, {"index": 389, "isLeaf": false, "children": [384, 388, 392, 395], "items": {"key": 1103, "value": 84.33}, "numberOfkeys": 1}, {"index": 390, "isLeaf": true, "children": [null, null, null, null], "items": {"key": 1102, "value": 84.05}, "numberOfkeys": 1}, {"index": 391, "isLeaf": true, "children": [null, null, null, null], "items": {"key": 1104, "value": 84.54}, "numberOfkeys": 1}, {"index": 392, "isLeaf": false, "children": [390, 391, 393, 394], "items": {"key": 1105, "value": 84.91}, "numberOfkeys": 1}, {"index": 393, "isLeaf": true, "children": [null, null, null, null], "items": {"key": 1106, "value": 85.24}, "numberOfkeys": 1}, {"index": 394, "isLeaf": true, "children": [null, null, null, null], "items": {"key": 1108, "value": 85.84}, "numberOfkeys": 1}, {"index": 395, "isLeaf": false, "children": [393, 394, 397, 399], "items": {"key": 1109, "value": 85.98}, "numberOfkeys": 1}, {"index": 396, "isLeaf": false, "children": [392, 395, 400, 403], "items": {"key": 1111, "value": 86.4}, "numberOfkeys": 1}, {"index": 397, "isLeaf": true, "children": [null, null, null, null], "items": {"key": 1110, "value": 86.21}, "numberOfkeys": 1}, {"index": 398, "isLeaf": false, "children": [389, 396, 404, 411], "items": {"key": 1115, "value": 87.21}, "numberOfkeys": 1}, {"index": 399, "isLeaf": true, "children": [null, null, null, null], "items": {"key": 1112, "value": 86.56}, "numberOfkeys": 1}, {"index": 400, "isLeaf": false, "children": [397, 399, 401, 402], "items": {"key": 1113, "value": 86.8}, "numberOfkeys": 1}, {"index": 401, "isLeaf": true, "children": [null, null, null, null], "items": {"key": 1114, "value": 87.03}, "numberOfkeys": 1}, {"index": 402, "isLeaf": true, "children": [null, null, null, null], "items": {"key": 1116, "value": 87.45}, "numberOfkeys": 1}, {"index": 403, "isLeaf": false, "children": [401, 402, 405, 406], "items": {"key": 1117, "value": 87.62}, "numberOfkeys": 1}, {"index": 404, "isLeaf": false, "children": [400, 403, 407, 410], "items": {"key": 1119, "value": 88.01}, "numberOfkeys": 1}, {"index": 405, "isLeaf": true, "children": [null, null, null, null], "items": {"key": 1118, "value": 87.8}, "numberOfkeys": 1}, {"index": 406, "isLeaf": true, "children": [null, null, null, null], "items": {"key": 1120, "value": 88.18}, "numberOfkeys": 1}, {"index": 407, "isLeaf": false, "children": [405, 406, 408, 409], "items": {"key": 1121, "value": 88.31}, "numberOfkeys": 1}, {"index": 408, "isLeaf": true, "children": [null, null, null, null], "items": {"key": 1122, "value": 88.57}, "numberOfkeys": 1}, {"index": 409, "isLeaf": true, "children": [null, null, null, null], "items": {"key": 1124, "value": 88.85}, "numberOfkeys": 1}, {"index": 410, "isLeaf": false, "children": [408, 409, 412, 415], "items": {"key": 1125, "value": 89.01}, "numberOfkeys": 1}, {"index": 411, "isLeaf": false, "children": [407, 410, 416, 419], "items": {"key": 1127, "value": 89.26}, "numberOfkeys": 1}, {"index": 412, "isLeaf": true, "children": [null, null, null, null], "items": {"key": 1126, "value": 89.13}, "numberOfkeys": 1}, {"index": 413, "isLeaf": false, "children": [404, 411, 420, 427], "items": {"key": 1131, "value": 90.03}, "numberOfkeys": 1}, {"index": 414, "isLeaf": false, "children": [398, 413, 429, 444], "items": {"key": 1139, "value": 91.45}, "numberOfkeys": 1}, {"index": 415, "isLeaf": true, "children": [null, null, null, null], "items": {"key": 1128, "value": 89.46}, "numberOfkeys": 1}, {"index": 416, "isLeaf": false, "children": [412, 415, 417, 418], "items": {"key": 1129, "value": 89.7}, "numberOfkeys": 1}, {"index": 417, "isLeaf": true, "children": [null, null, null, null], "items": {"key": 1130, "value": 89.85}, "numberOfkeys": 1}, {"index": 418, "isLeaf": true, "children": [null, null, null, null], "items": {"key": 1132, "value": 90.16}, "numberOfkeys": 1}, {"index": 419, "isLeaf": false, "children": [417, 418, 421, 422], "items": {"key": 1133, "value": 90.37}, "numberOfkeys": 1}, {"index": 420, "isLeaf": false, "children": [416, 419, 423, 426], "items": {"key": 1135, "value": 90.82}, "numberOfkeys": 1}, {"index": 421, "isLeaf": true, "children": [null, null, null, null], "items": {"key": 1134, "value": 90.55}, "numberOfkeys": 1}, {"index": 422, "isLeaf": true, "children": [null, null, null, null], "items": {"key": 1136, "value": 90.93}, "numberOfkeys": 1}, {"index": 423, "isLeaf": false, "children": [421, 422, 424, 425], "items": {"key": 1137, "value": 91.06}, "numberOfkeys": 1}, {"index": 424, "isLeaf": true, "children": [null, null, null, null], "items": {"key": 1138, "value": 91.25}, "numberOfkeys": 1}, {"index": 425, "isLeaf": true, "children": [null, null, null, null], "items": {"key": 1140, "value": 91.65}, "numberOfkeys": 1}, {"index": 426, "isLeaf": false, "children": [424, 425, 428, 430], "items": {"key": 1141, "value": 91.78}, "numberOfkeys": 1}, {"index": 427, "isLeaf": false, "children": [423, 426, 431, 434], "items": {"key": 1143, "value": 92.1}, "numberOfkeys": 1}, {"index": 428, "isLeaf": true, "children": [null, null, null, null], "items": {"key": 1142, "value": 91.94}, "numberOfkeys": 1}, {"index": 429, "isLeaf": false, "children": [420, 427, 435, 442], "items": {"key": 1147, "value": 92.75}, "numberOfkeys": 1}, {"index": 430, "isLeaf": true, "children": [null, null, null, null], "items": {"key": 1144, "value": 92.24}, "numberOfkeys": 1}, {"index": 431, "isLeaf": false, "children": [428, 430, 432, 433], "items": {"key": 1145, "value": 92.42}, "numberOfkeys": 1}, {"index": 432, "isLeaf": true, "children": [null, null, null, null], "items": {"key": 1146, "value": 92.55}, "numberOfkeys": 1}, {"index": 433, "isLeaf": true, "children": [null, null, null, null], "items": {"key": 1148, "value": 92.84}, "numberOfkeys": 1}, {"index": 434, "isLeaf": false, "children": [432, 433, 436, 437], "items": {"key": 1149, "value": 92.98}, "numberOfkeys": 1}, {"index": 435, "isLeaf": false, "children": [431, 434, 438, 441], "items": {"key": 1151, "value": 93.22}, "numberOfkeys": 1}, {"index": 436, "isLeaf": true, "children": [null, null, null, null], "items": {"key": 1150, "value": 93.07}, "numberOfkeys": 1}, {"index": 437, "isLeaf": true, "children": [null, null, null, null], "items": {"key": 1152, "value": 93.3}, "numberOfkeys": 1}, {"index": 438, "isLeaf": false, "children": [436, 437, 439, 440], "items": {"key": 1153, "value": 93.42}, "numberOfkeys": 1}, {"index": 439, "isLeaf": true, "children": [null, null, null, null], "items": {"key": 1154, "value": 93.56}, "numberOfkeys": 1}, {"index": 440, "isLeaf": true, "children": [null, null, null, null], "items": {"key": 1156, "value": 93.83}, "numberOfkeys": 1}, {"index": 441, "isLeaf": false, "children": [439, 440, 443, 446], "items": {"key": 1157, "value": 93.97}, "numberOfkeys": 1}, {"index": 442, "isLeaf": false, "children": [438, 441, 448, 451], "items": {"key": 1159, "value": 94.19}, "numberOfkeys": 1}, {"index": 443, "isLeaf": true, "children": [null, null, null, null], "items": {"key": 1158, "value": 94.14}, "numberOfkeys": 1}, {"index": 444, "isLeaf": false, "children": [435, 442, 452, 459], "items": {"key": 1163, "value": 94.64}, "numberOfkeys": 1}, {"index": 445, "isLeaf": false, "children": [429, 444, 461, 476], "items": {"key": 1171, "value": 95.29}, "numberOfkeys": 1}, {"index": 446, "isLeaf": true, "children": [null, null, null, null], "items": {"key": 1160, "value": 94.32}, "numberOfkeys": 1}, {"index": 447, "isLeaf": false, "children": [414, 445, 477, 508], "items": {"key": 1187, "value": 96.69}, "numberOfkeys": 1}, {"index": 448, "isLeaf": false, "children": [443, 446, 449, 450], "items": {"key": 1161, "value": 94.41}, "numberOfkeys": 1}, {"index": 449, "isLeaf": true, "children": [null, null, null, null], "items": {"key": 1162, "value": 94.57}, "numberOfkeys": 1}, {"index": 450, "isLeaf": true, "children": [null, null, null, null], "items": {"key": 1164, "value": 94.76}, "numberOfkeys": 1}, {"index": 451, "isLeaf": false, "children": [449, 450, 453, 454], "items": {"key": 1165, "value": 94.86}, "numberOfkeys": 1}, {"index": 452, "isLeaf": false, "children": [448, 451, 455, 458], "items": {"key": 1167, "value": 95.03}, "numberOfkeys": 1}, {"index": 453, "isLeaf": true, "children": [null, null, null, null], "items": {"key": 1166, "value": 94.95}, "numberOfkeys": 1}, {"index": 454, "isLeaf": true, "children": [null, null, null, null], "items": {"key": 1168, "value": 95.12}, "numberOfkeys": 1}, {"index": 455, "isLeaf": false, "children": [453, 454, 456, 457], "items": {"key": 1169, "value": 95.19}, "numberOfkeys": 1}, {"index": 456, "isLeaf": true, "children": [null, null, null, null], "items": {"key": 1170, "value": 95.25}, "numberOfkeys": 1}, {"index": 457, "isLeaf": true, "children": [null, null, null, null], "items": {"key": 1172, "value": 95.4}, "numberOfkeys": 1}, {"index": 458, "isLeaf": false, "children": [456, 457, 460, 462], "items": {"key": 1173, "value": 95.42}, "numberOfkeys": 1}, {"index": 459, "isLeaf": false, "children": [455, 458, 463, 466], "items": {"key": 1175, "value": 95.63}, "numberOfkeys": 1}, {"index": 460, "isLeaf": true, "children": [null, null, null, null], "items": {"key": 1174, "value": 95.54}, "numberOfkeys": 1}, {"index": 461, "isLeaf": false, "children": [452, 459, 467, 474], "items": {"key": 1179, "value": 96.01}, "numberOfkeys": 1}, {"index": 462, "isLeaf": true, "children": [null, null, null, null], "items": {"key": 1176, "value": 95.74}, "numberOfkeys": 1}, {"index": 463, "isLeaf": false, "children": [460, 462, 464, 465], "items": {"key": 1177, "value": 95.84}, "numberOfkeys": 1}, {"index": 464, "isLeaf": true, "children": [null, null, null, null], "items": {"key": 1178, "value": 95.92}, "numberOfkeys": 1}, {"index": 465, "isLeaf": true, "children": [null, null, null, null], "items": {"key": 1180, "value": 96.16}, "numberOfkeys": 1}, {"index": 466, "isLeaf": false, "children": [464, 465, 468, 469], "items": {"key": 1181, "value": 96.22}, "numberOfkeys": 1}, {"index": 467, "isLeaf": false, "children": [463, 466, 470, 473], "items": {"key": 1183, "value": 96.43}, "numberOfkeys": 1}, {"index": 468, "isLeaf": true, "children": [null, null, null, null], "items": {"key": 1182, "value": 96.36}, "numberOfkeys": 1}, {"index": 469, "isLeaf": true, "children": [null, null, null, null], "items": {"key": 1184, "value": 96.48}, "numberOfkeys": 1}, {"index": 470, "isLeaf": false, "children": [468, 469, 471, 472], "items": {"key": 1185, "value": 96.56}, "numberOfkeys": 1}, {"index": 471, "isLeaf": true, "children": [null, null, null, null], "items": {"key": 1186, "value": 96.64}, "numberOfkeys": 1}, {"index": 472, "isLeaf": true, "children": [null, null, null, null], "items": {"key": 1188, "value": 96.76}, "numberOfkeys": 1}, {"index": 473, "isLeaf": false, "children": [471, 472, 475, 478], "items": {"key": 1189, "value": 96.83}, "numberOfkeys": 1}, {"index": 474, "isLeaf": false, "children": [470, 473, 479, 482], "items": {"key": 1191, "value": 96.97}, "numberOfkeys": 1}, {"index": 475, "isLeaf": true, "children": [null, null, null, null], "items": {"key": 1190, "value": 96.91}, "numberOfkeys": 1}, {"index": 476, "isLeaf": false, "children": [467, 474, 483, 490], "items": {"key": 1195, "value": 97.27}, "numberOfkeys": 1}, {"index": 477, "isLeaf": false, "children": [461, 476, 492, 507], "items": {"key": 1203, "value": 97.75}, "numberOfkeys": 1}, {"index": 478, "isLeaf": true, "children": [null, null, null, null], "items": {"key": 1192, "value": 97.06}, "numberOfkeys": 1}, {"index": 479, "isLeaf": false, "children": [475, 478, 480, 481], "items": {"key": 1193, "value": 97.12}, "numberOfkeys": 1}, {"index": 480, "isLeaf": true, "children": [null, null, null, null], "items": {"key": 1194, "value": 97.19}, "numberOfkeys": 1}, {"index": 481, "isLeaf": true, "children": [null, null, null, null], "items": {"key": 1196, "value": 97.37}, "numberOfkeys": 1}, {"index": 482, "isLeaf": false, "children": [480, 481, 484, 485], "items": {"key": 1197, "value": 97.43}, "numberOfkeys": 1}, {"index": 483, "isLeaf": false, "children": [479, 482, 486, 489], "items": {"key": 1199, "value": 97.58}, "numberOfkeys": 1}, {"index": 484, "isLeaf": true, "children": [null, null, null, null], "items": {"key": 1198, "value": 97.53}, "numberOfkeys": 1}, {"index": 485, "isLeaf": true, "children": [null, null, null, null], "items": {"key": 1200, "value": 97.65}, "numberOfkeys": 1}, {"index": 486, "isLeaf": false, "children": [484, 485, 487, 488], "items": {"key": 1201, "value": 97.67}, "numberOfkeys": 1}, {"index": 487, "isLeaf": true, "children": [null, null, null, null], "items": {"key": 1202, "value": 97.72}, "numberOfkeys": 1}, {"index": 488, "isLeaf": true, "children": [null, null, null, null], "items": {"key": 1204, "value": 97.77}, "numberOfkeys": 1}, {"index": 489, "isLeaf": false, "children": [487, 488, 491, 493], "items": {"key": 1205, "value": 97.85}, "numberOfkeys": 1}, {"index": 490, "isLeaf": false, "children": [486, 489, 494, 497], "items": {"key": 1207, "value": 98.04}, "numberOfkeys": 1}, {"index": 491, "isLeaf": true, "children": [null, null, null, null], "items": {"key": 1206, "value": 97.94}, "numberOfkeys": 1}, {"index": 492, "isLeaf": false, "children": [483, 490, 498, 505], "items": {"key": 1211, "value": 98.17}, "numberOfkeys": 1}, {"index": 493, "isLeaf": true, "children": [null, null, null, null], "items": {"key": 1208, "value": 98.05}, "numberOfkeys": 1}, {"index": 494, "isLeaf": false, "children": [491, 493, 495, 496], "items": {"key": 1209, "value": 98.09}, "numberOfkeys": 1}, {"index": 495, "isLeaf": true, "children": [null, null, null, null], "items": {"key": 1210, "value": 98.13}, "numberOfkeys": 1}, {"index": 496, "isLeaf": true, "children": [null, null, null, null], "items": {"key": 1212, "value": 98.19}, "numberOfkeys": 1}, {"index": 497, "isLeaf": false, "children": [495, 496, 499, 500], "items": {"key": 1213, "value": 98.2}, "numberOfkeys": 1}, {"index": 498, "isLeaf": false, "children": [494, 497, 501, 504], "items": {"key": 1215, "value": 98.29}, "numberOfkeys": 1}, {"index": 499, "isLeaf": true, "children": [null, null, null, null], "items": {"key": 1214, "value": 98.25}, "numberOfkeys": 1}, {"index": 500, "isLeaf": true, "children": [null, null, null, null], "items": {"key": 1216, "value": 98.32}, "numberOfkeys": 1}, {"index": 501, "isLeaf": false, "children": [499, 500, 502, 503], "items": {"key": 1217, "value": 98.36}, "numberOfkeys": 1}, {"index": 502, "isLeaf": true, "children": [null, null, null, null], "items": {"key": 1218, "value": 98.37}, "numberOfkeys": 1}, {"index": 503, "isLeaf": true, "children": [null, null, null, null], "items": {"key": 1220, "value": 98.42}, "numberOfkeys": 1}, {"index": 504, "isLeaf": false, "children": [502, 503, 506, 509], "items": {"key": 1221, "value": 98.48}, "numberOfkeys": 1}, {"index": 505, "isLeaf": false, "children": [501, 504, 511, 517], "items": {"key": 1223, "value": 98.59}, "numberOfkeys": 1}, {"index": 506, "isLeaf": true, "children": [null, null, null, null], "items": {"key": 1222, "value": 98.55}, "numberOfkeys": 1}, {"index": 507, "isLeaf": false, "children": [498, 505, 518, 525], "items": {"key": 1227, "value": 98.75}, "numberOfkeys": 1}, {"index": 508, "isLeaf": false, "children": [492, 507, 527, 542], "items": {"key": 1235, "value": 98.94}, "numberOfkeys": 1}, {"index": 509, "isLeaf": true, "children": [null, null, null, null], "items": {"key": 1224, "value": 98.61}, "numberOfkeys": 1}, {"index": 510, "isLeaf": false, "children": [477, 508, 543, 574], "items": {"key": 1253, "value": 99.35}, "numberOfkeys": 1}, {"index": 511, "isLeaf": false, "children": [506, 509, 513, 516], "items": {"key": 1225, "value": 98.65}, "numberOfkeys": 1}, {"index": 512, "isLeaf": false, "children": [447, 510, 576, null], "items": {"key": 1219, "value": 98.39}, "numberOfkeys": 2}, {"index": 513, "isLeaf": true, "children": [null, null, null, null], "items": {"key": 1226, "value": 98.7}, "numberOfkeys": 1}, {"index": 514, "isLeaf": false, "children": [257, 515, null, null], "items": {"key": 963, "value": 35.17}, "numberOfkeys": 1}, {"index": 515, "isLeaf": false, "children": [385, 512, null, null], "items": {"key": 1091, "value": 81.17}, "numberOfkeys": 1}, {"index": 516, "isLeaf": true, "children": [null, null, null, null], "items": {"key": 1228, "value": 98.76}, "numberOfkeys": 1}, {"index": 517, "isLeaf": false, "children": [513, 516, 519, 520], "items": {"key": 1229, "value": 98.77}, "numberOfkeys": 1}, {"index": 518, "isLeaf": false, "children": [511, 517, 521, 524], "items": {"key": 1231, "value": 98.83}, "numberOfkeys": 1}, {"index": 519, "isLeaf": true, "children": [null, null, null, null], "items": {"key": 1230, "value": 98.81}, "numberOfkeys": 1}, {"index": 520, "isLeaf": true, "children": [null, null, null, null], "items": {"key": 1232, "value": 98.86}, "numberOfkeys": 1}, {"index": 521, "isLeaf": false, "children": [519, 520, 522, 523], "items": {"key": 1233, "value": 98.89}, "numberOfkeys": 1}, {"index": 522, "isLeaf": true, "children": [null, null, null, null], "items": {"key": 1234, "value": 98.9}, "numberOfkeys": 1}, {"index": 523, "isLeaf": true, "children": [null, null, null, null], "items": {"key": 1236, "value": 98.97}, "numberOfkeys": 1}, {"index": 524, "isLeaf": false, "children": [522, 523, 526, 528], "items": {"key": 1237, "value": 99.02}, "numberOfkeys": 1}, {"index": 525, "isLeaf": false, "children": [521, 524, 529, 532], "items": {"key": 1239, "value": 99.07}, "numberOfkeys": 1}, {"index": 526, "isLeaf": true, "children": [null, null, null, null], "items": {"key": 1238, "value": 99.04}, "numberOfkeys": 1}, {"index": 527, "isLeaf": false, "children": [518, 525, 533, 540], "items": {"key": 1244, "value": 99.16}, "numberOfkeys": 1}, {"index": 528, "isLeaf": true, "children": [null, null, null, null], "items": {"key": 1241, "value": 99.09}, "numberOfkeys": 1}, {"index": 529, "isLeaf": false, "children": [526, 528, 530, 531], "items": {"key": 1242, "value": 99.1}, "numberOfkeys": 1}, {"index": 530, "isLeaf": true, "children": [null, null, null, null], "items": {"key": 1243, "value": 99.15}, "numberOfkeys": 1}, {"index": 531, "isLeaf": true, "children": [null, null, null, null], "items": {"key": 1245, "value": 99.19}, "numberOfkeys": 1}, {"index": 532, "isLeaf": false, "children": [530, 531, 534, 535], "items": {"key": 1246, "value": 99.21}, "numberOfkeys": 1}, {"index": 533, "isLeaf": false, "children": [529, 532, 536, 539], "items": {"key": 1249, "value": 99.24}, "numberOfkeys": 1}, {"index": 534, "isLeaf": true, "children": [null, null, null, null], "items": {"key": 1247, "value": 99.23}, "numberOfkeys": 1}, {"index": 535, "isLeaf": true, "children": [null, null, null, null], "items": {"key": 1250, "value": 99.26}, "numberOfkeys": 1}, {"index": 536, "isLeaf": false, "children": [534, 535, 537, 538], "items": {"key": 1251, "value": 99.27}, "numberOfkeys": 1}, {"index": 537, "isLeaf": true, "children": [null, null, null, null], "items": {"key": 1252, "value": 99.32}, "numberOfkeys": 1}, {"index": 538, "isLeaf": true, "children": [null, null, null, null], "items": {"key": 1254, "value": 99.39}, "numberOfkeys": 1}, {"index": 539, "isLeaf": false, "children": [537, 538, 541, 544], "items": {"key": 1255, "value": 99.41}, "numberOfkeys": 1}, {"index": 540, "isLeaf": false, "children": [536, 539, 545, 548], "items": {"key": 1258, "value": 99.48}, "numberOfkeys": 1}, {"index": 541, "isLeaf": true, "children": [null, null, null, null], "items": {"key": 1257, "value": 99.45}, "numberOfkeys": 1}, {"index": 542, "isLeaf": false, "children": [533, 540, 549, 556], "items": {"key": 1263, "value": 99.53}, "numberOfkeys": 1}, {"index": 543, "isLeaf": false, "children": [527, 542, 558, 573], "items": {"key": 1275, "value": 99.67}, "numberOfkeys": 1}, {"index": 544, "isLeaf": true, "children": [null, null, null, null], "items": {"key": 1259, "value": 99.49}, "numberOfkeys": 1}, {"index": 545, "isLeaf": false, "children": [541, 544, 546, 547], "items": {"key": 1260, "value": 99.51}, "numberOfkeys": 1}, {"index": 546, "isLeaf": true, "children": [null, null, null, null], "items": {"key": 1262, "value": 99.52}, "numberOfkeys": 1}, {"index": 547, "isLeaf": true, "children": [null, null, null, null], "items": {"key": 1265, "value": 99.54}, "numberOfkeys": 1}, {"index": 548, "isLeaf": false, "children": [546, 547, 550, 551], "items": {"key": 1266, "value": 99.58}, "numberOfkeys": 1}, {"index": 549, "isLeaf": false, "children": [545, 548, 552, 555], "items": {"key": 1270, "value": 99.62}, "numberOfkeys": 1}, {"index": 550, "isLeaf": true, "children": [null, null, null, null], "items": {"key": 1269, "value": 99.61}, "numberOfkeys": 1}, {"index": 551, "isLeaf": true, "children": [null, null, null, null], "items": {"key": 1271, "value": 99.64}, "numberOfkeys": 1}, {"index": 552, "isLeaf": false, "children": [550, 551, 553, 554], "items": {"key": 1273, "value": 99.65}, "numberOfkeys": 1}, {"index": 553, "isLeaf": true, "children": [null, null, null, null], "items": {"key": 1274, "value": 99.66}, "numberOfkeys": 1}, {"index": 554, "isLeaf": true, "children": [null, null, null, null], "items": {"key": 1276, "value": 99.68}, "numberOfkeys": 1}, {"index": 555, "isLeaf": false, "children": [553, 554, 557, 559], "items": {"key": 1277, "value": 99.7}, "numberOfkeys": 1}, {"index": 556, "isLeaf": false, "children": [552, 555, 560, 563], "items": {"key": 1279, "value": 99.72}, "numberOfkeys": 1}, {"index": 557, "isLeaf": true, "children": [null, null, null, null], "items": {"key": 1278, "value": 99.71}, "numberOfkeys": 1}, {"index": 558, "isLeaf": false, "children": [549, 556, 564, 571], "items": {"key": 1289, "value": 99.78}, "numberOfkeys": 1}, {"index": 559, "isLeaf": true, "children": [null, null, null, null], "items": {"key": 1280, "value": 99.73}, "numberOfkeys": 1}, {"index": 560, "isLeaf": false, "children": [557, 559, 561, 562], "items": {"key": 1281, "value": 99.75}, "numberOfkeys": 1}, {"index": 561, "isLeaf": true, "children": [null, null, null, null], "items": {"key": 1282, "value": 99.77}, "numberOfkeys": 1}, {"index": 562, "isLeaf": true, "children": [null, null, null, null], "items": {"key": 1291, "value": 99.79}, "numberOfkeys": 1}, {"index": 563, "isLeaf": false, "children": [561, 562, 565, 566], "items": {"key": 1292, "value": 99.8}, "numberOfkeys": 1}, {"index": 564, "isLeaf": false, "children": [560, 563, 567, 570], "items": {"key": 1295, "value": 99.82}, "numberOfkeys": 1}, {"index": 565, "isLeaf": true, "children": [null, null, null, null], "items": {"key": 1293, "value": 99.81}, "numberOfkeys": 1}, {"index": 566, "isLeaf": true, "children": [null, null, null, null], "items": {"key": 1296, "value": 99.83}, "numberOfkeys": 1}, {"index": 567, "isLeaf": false, "children": [565, 566, 568, 569], "items": {"key": 1298, "value": 99.85}, "numberOfkeys": 1}, {"index": 568, "isLeaf": true, "children": [null, null, null, null], "items": {"key": 1299, "value": 99.86}, "numberOfkeys": 1}, {"index": 569, "isLeaf": true, "children": [null, null, null, null], "items": {"key": 1303, "value": 99.88}, "numberOfkeys": 1}, {"index": 570, "isLeaf": false, "children": [568, 569, 572, 575], "items": {"key": 1305, "value": 99.91}, "numberOfkeys": 1}, {"index": 571, "isLeaf": false, "children": [567, 570, 577, 580], "items": {"key": 1316, "value": 99.93}, "numberOfkeys": 1}, {"index": 572, "isLeaf": true, "children": [null, null, null, null], "items": {"key": 1309, "value": 99.92}, "numberOfkeys": 1}, {"index": 573, "isLeaf": false, "children": [564, 571, 581, null], "items": {"key": 1301, "value": 99.87}, "numberOfkeys": 2}, {"index": 574, "isLeaf": false, "children": [558, 573, null, null], "items": {"key": 1275, "value": 99.67}, "numberOfkeys": 1}, {"index": 575, "isLeaf": true, "children": [null, null, null, null], "items": {"key": 1317, "value": 99.94}, "numberOfkeys": 1}, {"index": 576, "isLeaf": false, "children": [543, 574, null, null], "items": {"key": 1253, "value": 99.35}, "numberOfkeys": 1}, {"index": 577, "isLeaf": false, "children": [572, 575, 578, 579], "items": {"key": 1342, "value": 99.95}, "numberOfkeys": 1}, {"index": 578, "isLeaf": true, "children": [null, null, null, null], "items": {"key": 1362, "value": 99.96}, "numberOfkeys": 1}, {"index": 579, "isLeaf": true, "children": [null, null, null, null], "items": {"key": 1376, "value": 99.98}, "numberOfkeys": 1}, {"index": 580, "isLeaf": false, "children": [578, 579, 582, null], "items": {"key": 1366, "value": 99.97}, "numberOfkeys": 2}, {"index": 581, "isLeaf": false, "children": [577, 580, null, null], "items": {"key": 1316, "value": 99.93}, "numberOfkeys": 1}, {"index": 582, "isLeaf": true, "children": [null, null, null, null], "items": {"key": 1384, "value": 99.99}, "numberOfkeys": 2}]